scm_config_clone/__init__.py
scm_config_clone/commands/deployments/__init__.py
scm_config_clone/commands/deployments/remote_networks.py
scm_config_clone/commands/network/__init__.py
scm_config_clone/commands/network/ike_crypto_profile.py
scm_config_clone/commands/network/ike_gateway.py
scm_config_clone/commands/network/ipsec_crypto_profile.py
scm_config_clone/commands/network/nat_rule.py
scm_config_clone/commands/objects/address.py
scm_config_clone/commands/objects/address_group.py
scm_config_clone/commands/objects/application.py
scm_config_clone/commands/objects/application_filters.py
scm_config_clone/commands/objects/application_group.py
scm_config_clone/commands/objects/dynamic_user_group.py
scm_config_clone/commands/objects/external_dynamic_lists.py
scm_config_clone/commands/objects/hip_objects.py
scm_config_clone/commands/objects/hip_profile.py
scm_config_clone/commands/objects/http_server_profile.py
scm_config_clone/commands/objects/log_forwarding_profile.py
scm_config_clone/commands/objects/quarantined_devices.py
scm_config_clone/commands/objects/region.py
scm_config_clone/commands/objects/schedule.py
scm_config_clone/commands/objects/service.py
scm_config_clone/commands/objects/service_group.py
scm_config_clone/commands/objects/syslog_server_profile.py
scm_config_clone/commands/objects/tag.py
scm_config_clone/commands/security/anti_spyware_profile.py
scm_config_clone/commands/security/decryption_profile.py
scm_config_clone/commands/security/dns_security_profile.py
scm_config_clone/commands/security/security_rule.py
scm_config_clone/commands/security/url_category.py
scm_config_clone/commands/security/vulnerability_protection_profile.py
scm_config_clone/commands/security/wildfire_antivirus_profile.py
scm_config_clone/commands/utilities/create_settings_file.py
scm_config_clone/main.py
scm_config_clone/utilities/__init__.py
scm_config_clone/utilities/compare_object_lists.py
scm_config_clone/utilities/parse_csv.py
scm_config_clone/utilities/settings.py
scm_config_clone-0.3.1.dist-info/LICENSE
scm_config_clone-0.3.1.dist-info/METADATA
scm_config_clone-0.3.1.dist-info/WHEEL
scm_config_clone-0.3.1.dist-info/entry_points.txt
scm_config_clone-0.3.1.dist-info/RECORD
