Metadata-Version: 2.3
Name: scm-config-clone
Version: 0.3.1
Summary: A command-line tool to clone configuration objects between Palo Alto Networks Strata Cloud Manager (SCM) tenants.
License: Apache 2.0
Author: Calvin Remsburg
Author-email: calvin@cdot.io
Requires-Python: >=3.10,<4.0
Classifier: License :: Other/Proprietary License
Classifier: Programming Language :: Python :: 3
Classifier: Programming Language :: Python :: 3.10
Classifier: Programming Language :: Python :: 3.11
Classifier: Programming Language :: Python :: 3.12
Classifier: Programming Language :: Python :: 3.13
Requires-Dist: pan-scm-sdk (>=0.3.43,<0.4.0)
Requires-Dist: pandas (>=2.2.3,<3.0.0)
Requires-Dist: pyyaml (>=6.0.2,<7.0.0)
Requires-Dist: setuptools (>=75.8.2,<76.0.0)
Requires-Dist: tabulate (>=0.9.0,<0.10.0)
Requires-Dist: typer (>=0.15.2,<0.16.0)
